README.md
setup.py
gym_hearts.egg-info/PKG-INFO
gym_hearts.egg-info/SOURCES.txt
gym_hearts.egg-info/dependency_links.txt
gym_hearts.egg-info/requires.txt
gym_hearts.egg-info/top_level.txt
gymhearts/__init__.py
gymhearts/env.py
gymhearts/evaluator.py
gymhearts/player.py
gymhearts/strategy.py