Metadata-Version: 1.0
Name: gym-hearts
Version: 0.0.3
Summary: OpenAI Gym Hearts Environment for Reinforcement Learning
Home-page: https://github.com/hisarack/gym-hearts
Author: Billy Yang
Author-email: radiohead0401@gmail.com
License: MIT
Platform: any
